Metadata-Version: 2.1
Name: s3-object-storage-client
Version: 0.2.1
Summary: s3 using tool
Home-page: https://github.com/susufqx/pyCeph
Author: susufqx
Author-email: jiangsulirui@gmail.com
License: MIT Licence
Keywords: pip,py_s3,s3,ceph,minio
Platform: any
License-File: LICENSE
